ArcGIS_Layout_Manager/LayoutManager.py
ArcGIS_Layout_Manager/__init__.py
ArcGIS_Layout_Manager/exceptions.py
ArcGIS_Layout_Manager/layout_elements.py
ArcGIS_Layout_Manager/table_of_contents_elements.py
ArcGIS_Layout_Manager-0.4.dist-info/DESCRIPTION.rst
ArcGIS_Layout_Manager-0.4.dist-info/METADATA
ArcGIS_Layout_Manager-0.4.dist-info/RECORD
ArcGIS_Layout_Manager-0.4.dist-info/WHEEL
ArcGIS_Layout_Manager-0.4.dist-info/metadata.json
ArcGIS_Layout_Manager-0.4.dist-info/top_level.txt
