Metadata-Version: 2.0
Name: ArcGIS-Layout-Manager
Version: 0.4
Summary: Helper for supporting multiple layouts in ArcGIS layout view
Home-page: https://github.com/namur007/ArcGIS_Layout_Manager
Author: namur007
Author-email: UNKNOWN
License: MIT
Platform: UNKNOWN
